anypubsub/__init__.py
anypubsub/interfaces.py
anypubsub/pubsub.py
anypubsub/backends/__init__.py
anypubsub/backends/amqp.py
anypubsub/backends/memory.py
anypubsub/backends/mongodb.py
anypubsub/backends/redis.py
anypubsub-0.6.dist-info/DESCRIPTION.rst
anypubsub-0.6.dist-info/METADATA
anypubsub-0.6.dist-info/RECORD
anypubsub-0.6.dist-info/WHEEL
anypubsub-0.6.dist-info/entry_points.txt
anypubsub-0.6.dist-info/metadata.json
anypubsub-0.6.dist-info/top_level.txt
tests/__init__.py
tests/test_pubsub.py
tests/test_backends/__init__.py
tests/test_backends/test_amqp.py
tests/test_backends/test_memory.py
tests/test_backends/test_mongodb.py
tests/test_backends/test_redis.py
