Metadata-Version: 2.0
Name: anypubsub
Version: 0.6
Summary: A generic interface wrapping multiple backends to provide a consistent pubsub API.
Home-page: http://github.com/simock85/anypubsub
Author: Simone Marzola
Author-email: marzolasimone@gmail.com
License: UNKNOWN
Keywords: pubsub pub/sub redis mongodb
Platform: UNKNOWN
Classifier: Development Status :: 3 - Alpha
Classifier: Intended Audience :: Developers
Classifier: Programming Language :: Python
Classifier: Programming Language :: Python :: 2.7
Classifier: Programming Language :: Python :: 3.3
Classifier: Programming Language :: Python :: 3.4
Classifier: Programming Language :: Python :: 3.5
Classifier: Programming Language :: Python :: 3.6
Classifier: Programming Language :: Python :: Implementation :: CPython
Classifier: Topic :: Software Development :: Libraries :: Python Modules
Classifier: License :: OSI Approved :: MIT License
Requires-Dist: six
Provides-Extra: amqp
Requires-Dist: amqp (>=1.4.9); extra == 'amqp'
Provides-Extra: mongodb
Requires-Dist: pymongo (>=3); extra == 'mongodb'
Provides-Extra: redis
Requires-Dist: redis (>2.10); extra == 'redis'
